{
  "environment": "web",
  "format": "../../../claat/render/template.html",
  "prefix": "https://quickstarts.snowflake.com/elements",
  "mainga": "UA-41491190-9",
  "updated": "2025-07-30T23:28:09-04:00",
  "id": "altr_get_started",
  "duration": 11,
  "title": "ALTR Quickstart - Data Access Control",
  "summary": "ALTR Quickstart - Data Access Control. Connect ALTR to snowflake and create an automatically enforced role based data access policy.",
  "source": "altr_get_started/altr_get_started.md",
  "theme": "",
  "status": [
    "published"
  ],
  "category": [
    "cybersecurity"
  ],
  "tags": [
    "dataowner",
    "datasecurity",
    "datasteward",
    "gettingstarted",
    "web"
  ],
  "feedback": "https://github.com/Snowflake-Labs/sfguides/issues",
  "url": "altr_get_started"
}
